[
    {
        "created_at": "2021-11-27T06:01:45Z",
        "entry_id": 1,
        "field1": "25.70000",
        "field2": "55.00000",
        "field3": "99.13918",
        "field4": "485.00000",
        "field5": "11.00000",
        "field6": "29425",
        "field7": "85"
    },
    {
        "created_at": "2021-11-27T06:07:45Z",
        "entry_id": 2,
        "field1": "25.80000",
        "field2": "55.00000",
        "field3": "113.84536",
        "field4": "486.00000",
        "field5": "13.00000",
        "field6": "29446",
        "field7": "85"
    },
    {
        "created_at": "2021-11-27T06:13:45Z",
        "entry_id": 3,
        "field1": "25.90000",
        "field2": "55.00000",
        "field3": "115.53441",
        "field4": "481.00000",
        "field5": "15.00000",
        "field6": "29493",
        "field7": "84"
    },
    {
        "created_at": "2021-11-27T06:19:45Z",
        "entry_id": 4,
        "field1": "25.90000",
        "field2": "55.40000",
        "field3": "110.22901",
        "field4": "480.00000",
        "field5": "12.00000",
        "field6": "29496",
        "field7": "84"
    },
    {
        "created_at": "2021-11-27T06:25:45Z",
        "entry_id": 5,
        "field1": "26.00000",
        "field2": "55.60000",
        "field3": "109.15885",
        "field4": "477.00000",
        "field5": "14.00000",
        "field6": "29520",
        "field7": "83"
    },
    {
        "created_at": "2021-11-27T06:31:45Z",
        "entry_id": 6,
        "field1": "26.10000",
        "field2": "55.30000",
        "field3": "110.5718",
        "field4": "473.00000",
        "field5": "18.00000",
        "field6": "29522",
        "field7": "83"
    },
    {
        "created_at": "2021-11-27T06:37:45Z",
        "entry_id": 7,
        "field1": "26.20000",
        "field2": "55.10000",
        "field3": "121.82802",
        "field4": "468.00000",
        "field5": "16.00000",
        "field6": "29569",
        "field7": "83"
    },
    {
        "created_at": "2021-11-27T06:43:45Z",
        "entry_id": 8,
        "field1": "26.30000",
        "field2": "54.80000",
        "field3": "115.12622",
        "field4": "468.00000",
        "field5": "20.00000",
        "field6": "29590",
        "field7": "82"
    },
    {
        "created_at": "2021-11-27T06:49:45Z",
        "entry_id": 9,
        "field1": "26.30000",
        "field2": "55.20000",
        "field3": "114.56154",
        "field4": "464.00000",
        "field5": "23.00000",
        "field6": "29620",
        "field7": "82"
    },
    {
        "created_at": "2021-11-27T06:55:45Z",
        "entry_id": 10,
        "field1": "26.40000",
        "field2": "55.30000",
        "field3": "127.63577",
        "field4": "460.00000",
        "field5": "25.00000",
        "field6": "29649",
        "field7": "82"
    },
    {
        "created_at": "2021-11-27T07:01:45Z",
        "entry_id": 11,
        "field1": "26.50000",
        "field2": "55.10000",
        "field3": "119.75024",
        "field4": "462.00000",
        "field5": "23.00000",
        "field6": "29651",
        "field7": "81"
    },
    {
        "created_at": "2021-11-27T07:07:45Z",
        "entry_id": 12,
        "field1": "26.60000",
        "field2": "55.30000",
        "field3": "123.83122",
        "field4": "457.00000",
        "field5": "19.00000",
        "field6": "29684",
        "field7": "81"
    },
    {
        "created_at": "2021-11-27T07:13:45Z",
        "entry_id": 13,
        "field1": "26.70000",
        "field2": "55.80000",
        "field3": "122.11155",
        "field4": "457.00000",
        "field5": "15.00000",
        "field6": "29692",
        "field7": "80"
    },
    {
        "created_at": "2021-11-27T07:19:45Z",
        "entry_id": 14,
        "field1": "26.70000",
        "field2": "55.40000",
        "field3": "130.30112",
        "field4": "456.00000",
        "field5": "16.00000",
        "field6": "29741",
        "field7": "80"
    },
    {
        "created_at": "2021-11-27T07:25:45Z",
        "entry_id": 15,
        "field1": "26.80000",
        "field2": "54.90000",
        "field3": "129.92621",
        "field4": "456.00000",
        "field5": "20.00000",
        "field6": "29772",
        "field7": "80"
    },
    {
        "created_at": "2021-11-27T07:31:45Z",
        "entry_id": 16,
        "field1": "26.90000",
        "field2": "54.70000",
        "field3": "136.77343",
        "field4": "455.00000",
        "field5": "18.00000",
        "field6": "29802",
        "field7": "79"
    },
    {
        "created_at": "2021-11-27T07:37:45Z",
        "entry_id": 17,
        "field1": "27.00000",
        "field2": "54.90000",
        "field3": "142.04371",
        "field4": "453.00000",
        "field5": "14.00000",
        "field6": "29839",
        "field7": "79"
    },
    {
        "created_at": "2021-11-27T07:43:45Z",
        "entry_id": 18,
        "field1": "27.10000",
        "field2": "54.50000",
        "field3": "143.64498",
        "field4": "454.00000",
        "field5": "16.00000",
        "field6": "29849",
        "field7": "78"
    },
    {
        "created_at": "2021-11-27T07:49:45Z",
        "entry_id": 19,
        "field1": "27.10000",
        "field2": "54.10000",
        "field3": "145.40135",
        "field4": "454.00000",
        "field5": "18.00000",
        "field6": "29879",
        "field7": "78"
    },
    {
        "created_at": "2021-11-27T07:55:45Z",
        "entry_id": 20,
        "field1": "27.20000",
        "field2": "53.80000",
        "field3": "156.4345",
        "field4": "456.00000",
        "field5": "14.00000",
        "field6": "29915",
        "field7": "78"
    },
    {
        "created_at": "2021-11-27T08:01:45Z",
        "entry_id": 21,
        "field1": "27.30000",
        "field2": "53.60000",
        "field3": "152.45036",
        "field4": "458.00000",
        "field5": "15.00000",
        "field6": "29932",
        "field7": "77"
    },
    {
        "created_at": "2021-11-27T08:07:45Z",
        "entry_id": 22,
        "field1": "27.40000",
        "field2": "53.10000",
        "field3": "162.43418",
        "field4": "459.00000",
        "field5": "14.00000",
        "field6": "29963",
        "field7": "77"
    },
    {
        "created_at": "2021-11-27T08:13:45Z",
        "entry_id": 23,
        "field1": "27.50000",
        "field2": "52.80000",
        "field3": "165.43005",
        "field4": "461.00000",
        "field5": "17.00000",
        "field6": "30003",
        "field7": "77"
    },
    {
        "created_at": "2021-11-27T08:19:45Z",
        "entry_id": 24,
        "field1": "27.50000",
        "field2": "53.30000",
        "field3": "173.45527",
        "field4": "458.00000",
        "field5": "18.00000",
        "field6": "30032",
        "field7": "76"
    },
    {
        "created_at": "2021-11-27T08:25:45Z",
        "entry_id": 25,
        "field1": "27.60000",
        "field2": "53.70000",
        "field3": "164.68689",
        "field4": "458.00000",
        "field5": "16.00000",
        "field6": "30036",
        "field7": "76"
    },
    {
        "created_at": "2021-11-27T08:31:45Z",
        "entry_id": 26,
        "field1": "27.70000",
        "field2": "53.80000",
        "field3": "157.6975",
        "field4": "454.00000",
        "field5": "20.00000",
        "field6": "30051",
        "field7": "75"
    },
    {
        "created_at": "2021-11-27T08:37:45Z",
        "entry_id": 27,
        "field1": "27.80000",
        "field2": "53.70000",
        "field3": "174.13982",
        "field4": "455.00000",
        "field5": "17.00000",
        "field6": "30072",
        "field7": "75"
    },
    {
        "created_at": "2021-11-27T08:43:45Z",
        "entry_id": 28,
        "field1": "27.90000",
        "field2": "53.40000",
        "field3": "171.32903",
        "field4": "454.00000",
        "field5": "18.00000",
        "field6": "30108",
        "field7": "75"
    },
    {
        "created_at": "2021-11-27T08:49:45Z",
        "entry_id": 29,
        "field1": "27.90000",
        "field2": "53.70000",
        "field3": "185.07448",
        "field4": "451.00000",
        "field5": "21.00000",
        "field6": "30152",
        "field7": "74"
    },
    {
        "created_at": "2021-11-27T08:55:45Z",
        "entry_id": 30,
        "field1": "28.00000",
        "field2": "53.90000",
        "field3": "178.18242",
        "field4": "450.00000",
        "field5": "17.00000",
        "field6": "30196",
        "field7": "74"
    },
    {
        "created_at": "2021-11-27T09:01:45Z",
        "entry_id": 31,
        "field1": "28.10000",
        "field2": "53.90000",
        "field3": "187.33437",
        "field4": "446.00000",
        "field5": "19.00000",
        "field6": "30204",
        "field7": "73"
    },
    {
        "created_at": "2021-11-27T09:07:45Z",
        "entry_id": 32,
        "field1": "28.20000",
        "field2": "54.40000",
        "field3": "192.5358",
        "field4": "446.00000",
        "field5": "21.00000",
        "field6": "30242",
        "field7": "73"
    },
    {
        "created_at": "2021-11-27T09:13:45Z",
        "entry_id": 33,
        "field1": "28.30000",
        "field2": "54.10000",
        "field3": "185.61578",
        "field4": "445.00000",
        "field5": "19.00000",
        "field6": "30292",
        "field7": "73"
    },
    {
        "created_at": "2021-11-27T09:19:45Z",
        "entry_id": 34,
        "field1": "28.30000",
        "field2": "54.00000",
        "field3": "185.72856",
        "field4": "443.00000",
        "field5": "18.00000",
        "field6": "30318",
        "field7": "72"
    },
    {
        "created_at": "2021-11-27T09:25:45Z",
        "entry_id": 35,
        "field1": "28.40000",
        "field2": "53.60000",
        "field3": "193.02265",
        "field4": "441.00000",
        "field5": "20.00000",
        "field6": "30350",
        "field7": "72"
    },
    {
        "created_at": "2021-11-27T09:31:45Z",
        "entry_id": 36,
        "field1": "28.50000",
        "field2": "53.80000",
        "field3": "201.57392",
        "field4": "442.00000",
        "field5": "21.00000",
        "field6": "30391",
        "field7": "72"
    },
    {
        "created_at": "2021-11-27T09:37:45Z",
        "entry_id": 37,
        "field1": "28.60000",
        "field2": "53.70000",
        "field3": "198.77329",
        "field4": "439.00000",
        "field5": "19.00000",
        "field6": "30419",
        "field7": "71"
    },
    {
        "created_at": "2021-11-27T09:43:45Z",
        "entry_id": 38,
        "field1": "28.70000",
        "field2": "53.90000",
        "field3": "194.96545",
        "field4": "441.00000",
        "field5": "23.00000",
        "field6": "30455",
        "field7": "71"
    },
    {
        "created_at": "2021-11-27T09:49:45Z",
        "entry_id": 39,
        "field1": "28.70000",
        "field2": "54.30000",
        "field3": "198.31383",
        "field4": "436.00000",
        "field5": "22.00000",
        "field6": "30497",
        "field7": "70"
    },
    {
        "created_at": "2021-11-27T09:55:45Z",
        "entry_id": 40,
        "field1": "28.80000",
        "field2": "54.00000",
        "field3": "199.67962",
        "field4": "437.00000",
        "field5": "21.00000",
        "field6": "30544",
        "field7": "70"
    },
    {
        "created_at": "2021-11-27T10:01:45Z",
        "entry_id": 41,
        "field1": "28.90000",
        "field2": "53.90000",
        "field3": "201.32815",
        "field4": "435.00000",
        "field5": "17.00000",
        "field6": "30568",
        "field7": "70"
    },
    {
        "created_at": "2021-11-27T10:07:45Z",
        "entry_id": 42,
        "field1": "29.00000",
        "field2": "54.30000",
        "field3": "203.03895",
        "field4": "430.00000",
        "field5": "21.00000",
        "field6": "30589",
        "field7": "69"
    },
    {
        "created_at": "2021-11-27T10:13:45Z",
        "entry_id": 43,
        "field1": "29.10000",
        "field2": "54.00000",
        "field3": "201.69071",
        "field4": "425.00000",
        "field5": "25.00000",
        "field6": "30615",
        "field7": "69"
    },
    {
        "created_at": "2021-11-27T10:19:45Z",
        "entry_id": 44,
        "field1": "29.10000",
        "field2": "54.40000",
        "field3": "197.93893",
        "field4": "425.00000",
        "field5": "28.00000",
        "field6": "30628",
        "field7": "69"
    },
    {
        "created_at": "2021-11-27T10:25:45Z",
        "entry_id": 45,
        "field1": "29.20000",
        "field2": "54.80000",
        "field3": "203.71212",
        "field4": "421.00000",
        "field5": "30.00000",
        "field6": "30651",
        "field7": "68"
    },
    {
        "created_at": "2021-11-27T10:31:45Z",
        "entry_id": 46,
        "field1": "29.30000",
        "field2": "55.20000",
        "field3": "211.46744",
        "field4": "420.00000",
        "field5": "30.00000",
        "field6": "30684",
        "field7": "68"
    },
    {
        "created_at": "2021-11-27T10:37:45Z",
        "entry_id": 47,
        "field1": "29.40000",
        "field2": "55.30000",
        "field3": "201.42484",
        "field4": "416.00000",
        "field5": "30.00000",
        "field6": "30728",
        "field7": "67"
    },
    {
        "created_at": "2021-11-27T10:43:45Z",
        "entry_id": 48,
        "field1": "29.50000",
        "field2": "54.90000",
        "field3": "203.4459",
        "field4": "419.00000",
        "field5": "29.00000",
        "field6": "30760",
        "field7": "67"
    },
    {
        "created_at": "2021-11-27T10:49:45Z",
        "entry_id": 49,
        "field1": "29.50000",
        "field2": "55.00000",
        "field3": "209.34222",
        "field4": "417.00000",
        "field5": "30.00000",
        "field6": "30804",
        "field7": "67"
    },
    {
        "created_at": "2021-11-27T10:55:45Z",
        "entry_id": 50,
        "field1": "29.60000",
        "field2": "54.90000",
        "field3": "221.53351",
        "field4": "419.00000",
        "field5": "30.00000",
        "field6": "30846",
        "field7": "66"
    },
    {
        "created_at": "2021-11-27T11:01:45Z",
        "entry_id": 51,
        "field1": "29.70000",
        "field2": "54.60000",
        "field3": "209.75418",
        "field4": "422.00000",
        "field5": "30.00000",
        "field6": "30854",
        "field7": "66"
    },
    {
        "created_at": "2021-11-27T11:07:45Z",
        "entry_id": 52,
        "field1": "29.80000",
        "field2": "54.40000",
        "field3": "203.77293",
        "field4": "423.00000",
        "field5": "30.00000",
        "field6": "30855",
        "field7": "65"
    },
    {
        "created_at": "2021-11-27T11:13:45Z",
        "entry_id": 53,
        "field1": "29.90000",
        "field2": "54.50000",
        "field3": "209.84162",
        "field4": "419.00000",
        "field5": "30.00000",
        "field6": "30882",
        "field7": "65"
    },
    {
        "created_at": "2021-11-27T11:19:45Z",
        "entry_id": 54,
        "field1": "29.90000",
        "field2": "54.90000",
        "field3": "214.32201",
        "field4": "419.00000",
        "field5": "30.00000",
        "field6": "30893",
        "field7": "65"
    },
    {
        "created_at": "2021-11-27T11:25:45Z",
        "entry_id": 55,
        "field1": "30.00000",
        "field2": "54.80000",
        "field3": "211.76507",
        "field4": "422.00000",
        "field5": "30.00000",
        "field6": "30898",
        "field7": "64"
    },
    {
        "created_at": "2021-11-27T11:31:45Z",
        "entry_id": 56,
        "field1": "30.10000",
        "field2": "55.00000",
        "field3": "205.31324",
        "field4": "420.00000",
        "field5": "30.00000",
        "field6": "30928",
        "field7": "64"
    },
    {
        "created_at": "2021-11-27T11:37:45Z",
        "entry_id": 57,
        "field1": "30.20000",
        "field2": "55.10000",
        "field3": "213.13099",
        "field4": "420.00000",
        "field5": "29.00000",
        "field6": "30974",
        "field7": "64"
    },
    {
        "created_at": "2021-11-27T11:43:45Z",
        "entry_id": 58,
        "field1": "30.30000",
        "field2": "54.80000",
        "field3": "203.47361",
        "field4": "418.00000",
        "field5": "30.00000",
        "field6": "31001",
        "field7": "63"
    },
    {
        "created_at": "2021-11-27T11:49:45Z",
        "entry_id": 59,
        "field1": "30.30000",
        "field2": "54.50000",
        "field3": "206.47217",
        "field4": "417.00000",
        "field5": "28.00000",
        "field6": "31020",
        "field7": "63"
    },
    {
        "created_at": "2021-11-27T11:55:45Z",
        "entry_id": 60,
        "field1": "30.40000",
        "field2": "54.90000",
        "field3": "220.45571",
        "field4": "417.00000",
        "field5": "24.00000",
        "field6": "31048",
        "field7": "62"
    },
    {
        "created_at": "2021-11-27T12:01:45Z",
        "entry_id": 61,
        "field1": "30.50000",
        "field2": "54.50000",
        "field3": "234.56759",
        "field4": "414.00000",
        "field5": "26.00000",
        "field6": "31080",
        "field7": "62"
    },
    {
        "created_at": "2021-11-27T12:07:45Z",
        "entry_id": 62,
        "field1": "30.40000",
        "field2": "54.50000",
        "field3": "227.81634",
        "field4": "410.00000",
        "field5": "30.00000",
        "field6": "31092",
        "field7": "62"
    },
    {
        "created_at": "2021-11-27T12:13:45Z",
        "entry_id": 63,
        "field1": "30.30000",
        "field2": "54.80000",
        "field3": "237.0212",
        "field4": "411.00000",
        "field5": "26.00000",
        "field6": "31095",
        "field7": "61"
    },
    {
        "created_at": "2021-11-27T12:19:45Z",
        "entry_id": 64,
        "field1": "30.30000",
        "field2": "54.80000",
        "field3": "237.39458",
        "field4": "407.00000",
        "field5": "25.00000",
        "field6": "31110",
        "field7": "61"
    },
    {
        "created_at": "2021-11-27T12:25:45Z",
        "entry_id": 65,
        "field1": "30.20000",
        "field2": "54.50000",
        "field3": "241.34913",
        "field4": "408.00000",
        "field5": "27.00000",
        "field6": "31112",
        "field7": "60"
    },
    {
        "created_at": "2021-11-27T12:31:45Z",
        "entry_id": 66,
        "field1": "30.10000",
        "field2": "54.70000",
        "field3": "256.38399",
        "field4": "404.00000",
        "field5": "23.00000",
        "field6": "31126",
        "field7": "60"
    },
    {
        "created_at": "2021-11-27T12:37:45Z",
        "entry_id": 67,
        "field1": "30.00000",
        "field2": "55.00000",
        "field3": "240.71238",
        "field4": "401.00000",
        "field5": "21.00000",
        "field6": "31139",
        "field7": "60"
    },
    {
        "created_at": "2021-11-27T12:43:45Z",
        "entry_id": 68,
        "field1": "29.90000",
        "field2": "55.20000",
        "field3": "254.58306",
        "field4": "401.00000",
        "field5": "18.00000",
        "field6": "31180",
        "field7": "59"
    },
    {
        "created_at": "2021-11-27T12:49:45Z",
        "entry_id": 69,
        "field1": "29.90000",
        "field2": "55.20000",
        "field3": "257.01083",
        "field4": "396.00000",
        "field5": "20.00000",
        "field6": "31189",
        "field7": "59"
    },
    {
        "created_at": "2021-11-27T12:55:45Z",
        "entry_id": 70,
        "field1": "29.80000",
        "field2": "54.80000",
        "field3": "260.73657",
        "field4": "398.00000",
        "field5": "22.00000",
        "field6": "31219",
        "field7": "59"
    },
    {
        "created_at": "2021-11-27T13:01:45Z",
        "entry_id": 71,
        "field1": "29.70000",
        "field2": "54.70000",
        "field3": "261.26221",
        "field4": "399.00000",
        "field5": "25.00000",
        "field6": "31222",
        "field7": "58"
    },
    {
        "created_at": "2021-11-27T13:07:45Z",
        "entry_id": 72,
        "field1": "29.60000",
        "field2": "54.50000",
        "field3": "260.47394",
        "field4": "400.00000",
        "field5": "23.00000",
        "field6": "31238",
        "field7": "58"
    },
    {
        "created_at": "2021-11-27T13:13:45Z",
        "entry_id": 73,
        "field1": "29.50000",
        "field2": "54.50000",
        "field3": "262.74476",
        "field4": "396.00000",
        "field5": "22.00000",
        "field6": "31253",
        "field7": "57"
    },
    {
        "created_at": "2021-11-27T13:19:45Z",
        "entry_id": 74,
        "field1": "29.50000",
        "field2": "54.40000",
        "field3": "260.44171",
        "field4": "399.00000",
        "field5": "20.00000",
        "field6": "31269",
        "field7": "57"
    },
    {
        "created_at": "2021-11-27T13:25:45Z",
        "entry_id": 75,
        "field1": "29.40000",
        "field2": "54.30000",
        "field3": "248.43332",
        "field4": "394.00000",
        "field5": "21.00000",
        "field6": "31312",
        "field7": "57"
    },
    {
        "created_at": "2021-11-27T13:31:45Z",
        "entry_id": 76,
        "field1": "29.30000",
        "field2": "54.70000",
        "field3": "250.79232",
        "field4": "391.00000",
        "field5": "24.00000",
        "field6": "31321",
        "field7": "56"
    },
    {
        "created_at": "2021-11-27T13:37:45Z",
        "entry_id": 77,
        "field1": "29.20000",
        "field2": "54.50000",
        "field3": "251.28092",
        "field4": "393.00000",
        "field5": "26.00000",
        "field6": "31359",
        "field7": "56"
    },
    {
        "created_at": "2021-11-27T13:43:45Z",
        "entry_id": 78,
        "field1": "29.10000",
        "field2": "54.30000",
        "field3": "238.08183",
        "field4": "391.00000",
        "field5": "22.00000",
        "field6": "31391",
        "field7": "55"
    },
    {
        "created_at": "2021-11-27T13:49:45Z",
        "entry_id": 79,
        "field1": "29.10000",
        "field2": "54.30000",
        "field3": "244.39371",
        "field4": "386.00000",
        "field5": "26.00000",
        "field6": "31412",
        "field7": "55"
    },
    {
        "created_at": "2021-11-27T13:55:45Z",
        "entry_id": 80,
        "field1": "29.00000",
        "field2": "54.60000",
        "field3": "247.81156",
        "field4": "385.00000",
        "field5": "30.00000",
        "field6": "31419",
        "field7": "55"
    },
    {
        "created_at": "2021-11-27T14:01:45Z",
        "entry_id": 81,
        "field1": "28.90000",
        "field2": "54.70000",
        "field3": "237.33074",
        "field4": "380.00000",
        "field5": "27.00000",
        "field6": "31420",
        "field7": "54"
    },
    {
        "created_at": "2021-11-27T14:07:45Z",
        "entry_id": 82,
        "field1": "28.80000",
        "field2": "54.90000",
        "field3": "242.21361",
        "field4": "379.00000",
        "field5": "25.00000",
        "field6": "31444",
        "field7": "54"
    },
    {
        "created_at": "2021-11-27T14:13:45Z",
        "entry_id": 83,
        "field1": "28.70000",
        "field2": "55.20000",
        "field3": "229.4516",
        "field4": "376.00000",
        "field5": "22.00000",
        "field6": "31484",
        "field7": "54"
    },
    {
        "created_at": "2021-11-27T14:19:45Z",
        "entry_id": 84,
        "field1": "28.70000",
        "field2": "55.20000",
        "field3": "221.28512",
        "field4": "377.00000",
        "field5": "18.00000",
        "field6": "31507",
        "field7": "53"
    },
    {
        "created_at": "2021-11-27T14:25:45Z",
        "entry_id": 85,
        "field1": "28.60000",
        "field2": "55.20000",
        "field3": "219.00058",
        "field4": "376.00000",
        "field5": "15.00000",
        "field6": "31540",
        "field7": "53"
    },
    {
        "created_at": "2021-11-27T14:31:45Z",
        "entry_id": 86,
        "field1": "28.50000",
        "field2": "55.20000",
        "field3": "214.00365",
        "field4": "372.00000",
        "field5": "16.00000",
        "field6": "31550",
        "field7": "52"
    },
    {
        "created_at": "2021-11-27T14:37:45Z",
        "entry_id": 87,
        "field1": "28.40000",
        "field2": "55.50000",
        "field3": "215.47199",
        "field4": "367.00000",
        "field5": "13.00000",
        "field6": "31582",
        "field7": "52"
    },
    {
        "created_at": "2021-11-27T14:43:45Z",
        "entry_id": 88,
        "field1": "28.30000",
        "field2": "55.20000",
        "field3": "208.23044",
        "field4": "367.00000",
        "field5": "15.00000",
        "field6": "31611",
        "field7": "52"
    },
    {
        "created_at": "2021-11-27T14:49:45Z",
        "entry_id": 89,
        "field1": "28.30000",
        "field2": "55.10000",
        "field3": "205.50172",
        "field4": "369.00000",
        "field5": "19.00000",
        "field6": "31613",
        "field7": "51"
    },
    {
        "created_at": "2021-11-27T14:55:45Z",
        "entry_id": 90,
        "field1": "28.20000",
        "field2": "54.80000",
        "field3": "198.44564",
        "field4": "367.00000",
        "field5": "23.00000",
        "field6": "31645",
        "field7": "51"
    },
    {
        "created_at": "2021-11-27T15:01:45Z",
        "entry_id": 91,
        "field1": "28.10000",
        "field2": "55.10000",
        "field3": "195.55167",
        "field4": "363.00000",
        "field5": "19.00000",
        "field6": "31654",
        "field7": "50"
    },
    {
        "created_at": "2021-11-27T15:07:45Z",
        "entry_id": 92,
        "field1": "28.00000",
        "field2": "55.60000",
        "field3": "186.79348",
        "field4": "364.00000",
        "field5": "16.00000",
        "field6": "31697",
        "field7": "50"
    },
    {
        "created_at": "2021-11-27T15:13:45Z",
        "entry_id": 93,
        "field1": "27.90000",
        "field2": "56.00000",
        "field3": "183.86042",
        "field4": "360.00000",
        "field5": "20.00000",
        "field6": "31709",
        "field7": "50"
    },
    {
        "created_at": "2021-11-27T15:19:45Z",
        "entry_id": 94,
        "field1": "27.90000",
        "field2": "56.40000",
        "field3": "179.54418",
        "field4": "361.00000",
        "field5": "22.00000",
        "field6": "31755",
        "field7": "49"
    },
    {
        "created_at": "2021-11-27T15:25:45Z",
        "entry_id": 95,
        "field1": "27.80000",
        "field2": "56.60000",
        "field3": "178.59084",
        "field4": "361.00000",
        "field5": "26.00000",
        "field6": "31780",
        "field7": "49"
    },
    {
        "created_at": "2021-11-27T15:31:45Z",
        "entry_id": 96,
        "field1": "27.70000",
        "field2": "56.30000",
        "field3": "176.42341",
        "field4": "362.00000",
        "field5": "27.00000",
        "field6": "31829",
        "field7": "49"
    },
    {
        "created_at": "2021-11-27T15:37:45Z",
        "entry_id": 97,
        "field1": "27.60000",
        "field2": "56.20000",
        "field3": "168.40225",
        "field4": "362.00000",
        "field5": "25.00000",
        "field6": "31872",
        "field7": "48"
    },
    {
        "created_at": "2021-11-27T15:43:45Z",
        "entry_id": 98,
        "field1": "27.50000",
        "field2": "56.40000",
        "field3": "157.09017",
        "field4": "357.00000",
        "field5": "28.00000",
        "field6": "31899",
        "field7": "48"
    },
    {
        "created_at": "2021-11-27T15:49:45Z",
        "entry_id": 99,
        "field1": "27.50000",
        "field2": "56.10000",
        "field3": "162.61892",
        "field4": "355.00000",
        "field5": "26.00000",
        "field6": "31938",
        "field7": "47"
    },
    {
        "created_at": "2021-11-27T15:55:45Z",
        "entry_id": 100,
        "field1": "27.40000",
        "field2": "56.40000",
        "field3": "167.12952",
        "field4": "353.00000",
        "field5": "23.00000",
        "field6": "31980",
        "field7": "47"
    },
    {
        "created_at": "2021-11-27T16:01:45Z",
        "entry_id": 101,
        "field1": "27.30000",
        "field2": "56.00000",
        "field3": "149.61603",
        "field4": "355.00000",
        "field5": "21.00000",
        "field6": "32001",
        "field7": "47"
    },
    {
        "created_at": "2021-11-27T16:07:45Z",
        "entry_id": 102,
        "field1": "27.20000",
        "field2": "56.10000",
        "field3": "154.68725",
        "field4": "356.00000",
        "field5": "17.00000",
        "field6": "32026",
        "field7": "46"
    },
    {
        "created_at": "2021-11-27T16:13:45Z",
        "entry_id": 103,
        "field1": "27.10000",
        "field2": "55.90000",
        "field3": "145.42",
        "field4": "354.00000",
        "field5": "19.00000",
        "field6": "32071",
        "field7": "46"
    },
    {
        "created_at": "2021-11-27T16:19:45Z",
        "entry_id": 104,
        "field1": "27.10000",
        "field2": "55.70000",
        "field3": "152.29341",
        "field4": "354.00000",
        "field5": "16.00000",
        "field6": "32118",
        "field7": "46"
    },
    {
        "created_at": "2021-11-27T16:25:45Z",
        "entry_id": 105,
        "field1": "27.00000",
        "field2": "55.50000",
        "field3": "149.14774",
        "field4": "352.00000",
        "field5": "18.00000",
        "field6": "32133",
        "field7": "45"
    },
    {
        "created_at": "2021-11-27T16:31:45Z",
        "entry_id": 106,
        "field1": "26.90000",
        "field2": "55.80000",
        "field3": "152.77618",
        "field4": "353.00000",
        "field5": "17.00000",
        "field6": "32138",
        "field7": "45"
    },
    {
        "created_at": "2021-11-27T16:37:45Z",
        "entry_id": 107,
        "field1": "26.80000",
        "field2": "56.20000",
        "field3": "147.5306",
        "field4": "350.00000",
        "field5": "21.00000",
        "field6": "32187",
        "field7": "44"
    },
    {
        "created_at": "2021-11-27T16:43:45Z",
        "entry_id": 108,
        "field1": "26.70000",
        "field2": "56.60000",
        "field3": "158.36461",
        "field4": "346.00000",
        "field5": "24.00000",
        "field6": "32218",
        "field7": "44"
    },
    {
        "created_at": "2021-11-27T16:49:45Z",
        "entry_id": 109,
        "field1": "26.70000",
        "field2": "56.20000",
        "field3": "151.35754",
        "field4": "347.00000",
        "field5": "27.00000",
        "field6": "32226",
        "field7": "44"
    },
    {
        "created_at": "2021-11-27T16:55:45Z",
        "entry_id": 110,
        "field1": "26.60000",
        "field2": "55.90000",
        "field3": "152.27938",
        "field4": "348.00000",
        "field5": "28.00000",
        "field6": "32258",
        "field7": "43"
    },
    {
        "created_at": "2021-11-27T17:01:45Z",
        "entry_id": 111,
        "field1": "26.50000",
        "field2": "56.20000",
        "field3": "149.93487",
        "field4": "345.00000",
        "field5": "26.00000",
        "field6": "32270",
        "field7": "43"
    },
    {
        "created_at": "2021-11-27T17:07:45Z",
        "entry_id": 112,
        "field1": "26.40000",
        "field2": "56.30000",
        "field3": "144.72844",
        "field4": "347.00000",
        "field5": "28.00000",
        "field6": "32277",
        "field7": "42"
    },
    {
        "created_at": "2021-11-27T17:13:45Z",
        "entry_id": 113,
        "field1": "26.30000",
        "field2": "55.90000",
        "field3": "141.46931",
        "field4": "342.00000",
        "field5": "27.00000",
        "field6": "32322",
        "field7": "42"
    },
    {
        "created_at": "2021-11-27T17:19:45Z",
        "entry_id": 114,
        "field1": "26.30000",
        "field2": "56.40000",
        "field3": "154.23108",
        "field4": "339.00000",
        "field5": "25.00000",
        "field6": "32371",
        "field7": "42"
    },
    {
        "created_at": "2021-11-27T17:25:45Z",
        "entry_id": 115,
        "field1": "26.20000",
        "field2": "56.80000",
        "field3": "157.06882",
        "field4": "340.00000",
        "field5": "28.00000",
        "field6": "32420",
        "field7": "41"
    },
    {
        "created_at": "2021-11-27T17:31:45Z",
        "entry_id": 116,
        "field1": "26.10000",
        "field2": "56.60000",
        "field3": "142.26346",
        "field4": "337.00000",
        "field5": "30.00000",
        "field6": "32439",
        "field7": "41"
    },
    {
        "created_at": "2021-11-27T17:37:45Z",
        "entry_id": 117,
        "field1": "26.00000",
        "field2": "56.90000",
        "field3": "141.79295",
        "field4": "335.00000",
        "field5": "30.00000",
        "field6": "32464",
        "field7": "41"
    },
    {
        "created_at": "2021-11-27T17:43:45Z",
        "entry_id": 118,
        "field1": "25.90000",
        "field2": "57.20000",
        "field3": "139.08605",
        "field4": "338.00000",
        "field5": "30.00000",
        "field6": "32481",
        "field7": "40"
    },
    {
        "created_at": "2021-11-27T17:49:45Z",
        "entry_id": 119,
        "field1": "25.90000",
        "field2": "57.70000",
        "field3": "125.84321",
        "field4": "334.00000",
        "field5": "30.00000",
        "field6": "32524",
        "field7": "40"
    },
    {
        "created_at": "2021-11-27T17:55:45Z",
        "entry_id": 120,
        "field1": "25.80000",
        "field2": "57.20000",
        "field3": "124.04033",
        "field4": "329.00000",
        "field5": "30.00000",
        "field6": "32570",
        "field7": "39"
    }
]